<?xml version="1.0" encoding="utf-8" ?><dwsync><file name="clip-line.js" server="192.168.0.31//var/www/html/" local="3473158208" remote="12064845169" /><file name="delaunay.js" server="192.168.0.31//var/www/html/" local="3473158208" remote="12064845169" /><file name="geom.js" server="192.168.0.31//var/www/html/" local="3473158208" remote="12064845169" /><file name="hull.js" server="192.168.0.31//var/www/html/" local="3473158208" remote="12064845169" /><file name="index.js" server="192.168.0.31//var/www/html/" local="3473158208" remote="12064845169" /><file name="point.js" server="192.168.0.31//var/www/html/" local="3473158208" remote="12064845169" /><file name="polygon.js" server="192.168.0.31//var/www/html/" local="3473158208" remote="12064845170" /><file name="quadtree.js" server="192.168.0.31//var/www/html/" local="3473158208" remote="12064845170" /><file name="voronoi.js" server="192.168.0.31//var/www/html/" local="3473158208" remote="12064845170" /></dwsync>